pysearchlite/__init__.py
pysearchlite/search_engine.py
pysearchlite/commands/__init__.py
pysearchlite/commands/build_index.py
pysearchlite/commands/do_query.py
pysearchlite/commands/main.py
pysearchlite-0.2.2.dist-info/LICENSE
pysearchlite-0.2.2.dist-info/METADATA
pysearchlite-0.2.2.dist-info/WHEEL
pysearchlite-0.2.2.dist-info/top_level.txt
pysearchlite-0.2.2.dist-info/RECORD
